arithmo_mcp_server/__init__.py
arithmo_mcp_server/calculator.py
arithmo_mcp_server/server.py
arithmo_mcp_server-0.1.0.dist-info/METADATA
arithmo_mcp_server-0.1.0.dist-info/WHEEL
arithmo_mcp_server-0.1.0.dist-info/entry_points.txt
arithmo_mcp_server-0.1.0.dist-info/top_level.txt
arithmo_mcp_server-0.1.0.dist-info/RECORD
