Metadata-Version: 2.4
Name: arithmo_mcp_server
Version: 0.1.0
Summary: An MCP server providing fast arithmetic operations.
Author-email: VARUN SAI BANDI <varunsai.srinivas@gmail.com>
Project-URL: Repository, https://github.com/varunidealabs/arithmo_mcp_server.git
Requires-Python: >=3.10
Requires-Dist: mcp
